<config>
	<globalProperties>
		<globalProperty>
			<property>layout.address.format</property>
			<value>&lt;org.openmrs.layout.address.AddressTemplate&gt;
  &lt;nameMappings&gt;
    &lt;entry&gt;
      &lt;string&gt;country&lt;/string&gt;
      &lt;string&gt;Country&lt;/string&gt;
    &lt;/entry&gt;
    &lt;entry&gt;
      &lt;string&gt;stateProvince&lt;/string&gt;
      &lt;string&gt;Province&lt;/string&gt;
    &lt;/entry&gt;
    &lt;entry&gt;
      &lt;string&gt;countyDistrict&lt;/string&gt;
      &lt;string&gt;District&lt;/string&gt;
    &lt;/entry&gt;
    &lt;entry&gt;
      &lt;string&gt;address1&lt;/string&gt;
      &lt;string&gt;Commune&lt;/string&gt;
    &lt;/entry&gt;
    &lt;entry&gt;
      &lt;string&gt;cityVillage&lt;/string&gt;
      &lt;string&gt;Village&lt;/string&gt;
    &lt;/entry&gt;
  &lt;/nameMappings&gt;
  &lt;sizeMappings&gt;
    &lt;entry&gt;
      &lt;string&gt;country&lt;/string&gt;
      &lt;string&gt;40&lt;/string&gt;
    &lt;/entry&gt;
    &lt;entry&gt;
      &lt;string&gt;stateProvince&lt;/string&gt;
      &lt;string&gt;40&lt;/string&gt;
    &lt;/entry&gt;
    &lt;entry&gt;
      &lt;string&gt;countyDistrict&lt;/string&gt;
      &lt;string&gt;40&lt;/string&gt;
    &lt;/entry&gt;
    &lt;entry&gt;
      &lt;string&gt;address1&lt;/string&gt;
      &lt;string&gt;40&lt;/string&gt;
    &lt;/entry&gt;
    &lt;entry&gt;
      &lt;string&gt;cityVillage&lt;/string&gt;
      &lt;string&gt;40&lt;/string&gt;
    &lt;/entry&gt;
  &lt;/sizeMappings&gt;
  &lt;elementDefaults&gt;
    &lt;entry&gt;
      &lt;string&gt;country&lt;/string&gt;
      &lt;string&gt;addresshierarchy.cambodia&lt;/string&gt;
    &lt;/entry&gt;
  &lt;/elementDefaults&gt;
  &lt;lineByLineFormat&gt;
    &lt;string&gt;cityVillage, address1&lt;/string&gt;
    &lt;string&gt;countyDistrict, stateProvince&lt;/string&gt;
    &lt;string&gt;country&lt;/string&gt;
  &lt;/lineByLineFormat&gt;
  &lt;maxTokens&gt;0&lt;/maxTokens&gt;
&lt;/org.openmrs.layout.address.AddressTemplate&gt;</value>
		</globalProperty>
	</globalProperties>
</config>